supernote/__init__.py
supernote/alembic.ini
supernote/py.typed
supernote/alembic/__init__.py
supernote/alembic/env.py
supernote/alembic/script.py.mako
supernote/alembic/versions/0543a383957b_initial_schema.py
supernote/cli/__init__.py
supernote/cli/admin.py
supernote/cli/client.py
supernote/cli/main.py
supernote/cli/notebook.py
supernote/cli/server.py
supernote/client/__init__.py
supernote/client/admin.py
supernote/client/api.py
supernote/client/api_model.py
supernote/client/auth.py
supernote/client/client.py
supernote/client/device.py
supernote/client/exceptions.py
supernote/client/extended.py
supernote/client/hashing.py
supernote/client/login_client.py
supernote/client/schedule.py
supernote/client/summary.py
supernote/client/web.py
supernote/models/__init__.py
supernote/models/auth.py
supernote/models/base.py
supernote/models/equipment.py
supernote/models/extended.py
supernote/models/file_common.py
supernote/models/file_device.py
supernote/models/file_web.py
supernote/models/schedule.py
supernote/models/summary.py
supernote/models/system.py
supernote/models/user.py
supernote/notebook/__init__.py
supernote/notebook/color.py
supernote/notebook/converter.py
supernote/notebook/decoder.py
supernote/notebook/exceptions.py
supernote/notebook/fileformat.py
supernote/notebook/manipulator.py
supernote/notebook/parser.py
supernote/notebook/utils.py
supernote/server/__init__.py
supernote/server/app.py
supernote/server/config.py
supernote/server/constants.py
supernote/server/events.py
supernote/server/exceptions.py
supernote/server/db/__init__.py
supernote/server/db/base.py
supernote/server/db/migrations.py
supernote/server/db/session.py
supernote/server/db/models/__init__.py
supernote/server/db/models/device.py
supernote/server/db/models/file.py
supernote/server/db/models/kv.py
supernote/server/db/models/login_record.py
supernote/server/db/models/note_processing.py
supernote/server/db/models/schedule.py
supernote/server/db/models/summary.py
supernote/server/db/models/user.py
supernote-0.14.6.dist-info/licenses/LICENSE
supernote-0.14.6.dist-info/METADATA
supernote-0.14.6.dist-info/WHEEL
supernote-0.14.6.dist-info/entry_points.txt
supernote-0.14.6.dist-info/top_level.txt
supernote-0.14.6.dist-info/RECORD
