Metadata-Version: 2.4
Name: supernote
Version: 0.14.6
Summary: All-in-one toolkit for Supernote devices: parse notebooks, self-host services, access services
Author-email: jya <jya@wizmy.net>, Allen Porter <allen.porter@gmail.com>
License-Expression: Apache-2.0
Project-URL: Source, https://github.com/allenporter/supernote
Requires-Python: >=3.13
License-File: LICENSE
Requires-Dist: colour>=0.1.5
Requires-Dist: numpy>=1.19.0
Requires-Dist: Pillow>=7.2.0
Requires-Dist: potracer>=0.0.1
Requires-Dist: pypng>=0.0.20
Requires-Dist: reportlab>=3.6.1
Requires-Dist: svgwrite>=1.4
Provides-Extra: client
Requires-Dist: aiohttp; extra == "client"
Requires-Dist: requests; extra == "client"
Requires-Dist: tqdm; extra == "client"
Provides-Extra: server
Requires-Dist: aiohttp>=3.13.2; extra == "server"
Requires-Dist: mashumaro>=3.17; extra == "server"
Requires-Dist: pyyaml>=6.0; extra == "server"
Requires-Dist: PyJWT>=2.10.1; extra == "server"
Requires-Dist: SQLAlchemy[asyncio]>=2.0.0; extra == "server"
Requires-Dist: alembic>=1.13.0; extra == "server"
Requires-Dist: aiosqlite>=0.19.0; extra == "server"
Requires-Dist: aiofiles>=25.1.0; extra == "server"
Requires-Dist: aiohttp-remotes>=1.3.0; extra == "server"
Requires-Dist: google-genai>=1.57.0; extra == "server"
Requires-Dist: mcp>=1.25.0; extra == "server"
Requires-Dist: aiohttp-asgi>=0.6.1; extra == "server"
Provides-Extra: all
Requires-Dist: supernote[client,server]; extra == "all"
Dynamic: license-file
